CHANGELOG.rst
LICENSE
MANIFEST.in
README.md
arxiv_collector.py
setup.py
arxiv_collector.egg-info/PKG-INFO
arxiv_collector.egg-info/SOURCES.txt
arxiv_collector.egg-info/dependency_links.txt
arxiv_collector.egg-info/entry_points.txt
arxiv_collector.egg-info/top_level.txt