Metadata-Version: 2.1
Name: arxiv-collector
Version: 0.3.4
Summary: A small script to collect LaTeX sources for upload to the arXiv
Home-page: https://github.com/dougalsutherland/arxiv-collector
Author: Dougal J. Sutherland
Author-email: dougal@gmail.com
License: UNKNOWN
Platform: UNKNOWN
Classifier: Programming Language :: Python :: 2
Classifier: Programming Language :: Python :: 3
Classifier: License :: OSI Approved :: BSD License
Classifier: Operating System :: MacOS
Classifier: Operating System :: POSIX
